forexconnect-1.6.43.data/purelib/forexconnect/EachRowListener.py
forexconnect-1.6.43.data/purelib/forexconnect/ForexConnect.py
forexconnect-1.6.43.data/purelib/forexconnect/LiveHistory.py
forexconnect-1.6.43.data/purelib/forexconnect/ResponseListener.py
forexconnect-1.6.43.data/purelib/forexconnect/SessionStatusListener.py
forexconnect-1.6.43.data/purelib/forexconnect/TableListener.py
forexconnect-1.6.43.data/purelib/forexconnect/TableManagerListener.py
forexconnect-1.6.43.data/purelib/forexconnect/__init__.py
forexconnect-1.6.43.data/purelib/forexconnect/common.py
forexconnect-1.6.43.data/purelib/forexconnect/errors.py
forexconnect-1.6.43.data/purelib/forexconnect/lib/ForexConnect.dll
forexconnect-1.6.43.data/purelib/forexconnect/lib/__init__.py
forexconnect-1.6.43.data/purelib/forexconnect/lib/api-ms-win-core-console-l1-1-0.dll
forexconnect-1.6.43.data/purelib/forexconnect/lib/api-ms-win-core-datetime-l1-1-0.dll
forexconnect-1.6.43.data/purelib/forexconnect/lib/api-ms-win-core-debug-l1-1-0.dll
forexconnect-1.6.43.data/purelib/forexconnect/lib/api-ms-win-core-errorhandling-l1-1-0.dll
forexconnect-1.6.43.data/purelib/forexconnect/lib/api-ms-win-core-file-l1-1-0.dll
forexconnect-1.6.43.data/purelib/forexconnect/lib/api-ms-win-core-file-l1-2-0.dll
forexconnect-1.6.43.data/purelib/forexconnect/lib/api-ms-win-core-file-l2-1-0.dll
forexconnect-1.6.43.data/purelib/forexconnect/lib/api-ms-win-core-handle-l1-1-0.dll
forexconnect-1.6.43.data/purelib/forexconnect/lib/api-ms-win-core-heap-l1-1-0.dll
forexconnect-1.6.43.data/purelib/forexconnect/lib/api-ms-win-core-interlocked-l1-1-0.dll
forexconnect-1.6.43.data/purelib/forexconnect/lib/api-ms-win-core-libraryloader-l1-1-0.dll
forexconnect-1.6.43.data/purelib/forexconnect/lib/api-ms-win-core-localization-l1-2-0.dll
forexconnect-1.6.43.data/purelib/forexconnect/lib/api-ms-win-core-memory-l1-1-0.dll
forexconnect-1.6.43.data/purelib/forexconnect/lib/api-ms-win-core-namedpipe-l1-1-0.dll
forexconnect-1.6.43.dist-info/LICENSE.txt
forexconnect-1.6.43.dist-info/METADATA
forexconnect-1.6.43.dist-info/RECORD
forexconnect-1.6.43.dist-info/WHEEL
forexconnect-1.6.43.dist-info/top_level.txt
