Metadata-Version: 2.1
Name: forexconnect
Version: 1.6.43
Summary: ForexConnect API is a trading API for the FXCM Group: https://www.fxcm.com/uk/
Home-page: https://github.com/gehtsoft/forex-connect
Author: Gehtsoft USA, LLC
Author-email: contact@gehtsoftusa.com
License: Other/Proprietary License
Platform: UNKNOWN
License-File: LICENSE
